alexandria/__init__.py
alexandria/logic.py
alexandria/paths.py
alexandria/regex.py
alexandria/sys.py
alexandria/data_structs/__init__.py
alexandria/data_structs/array.py
alexandria/data_structs/datetime.py
alexandria/data_structs/string.py
alexandria/file/__init__.py
alexandria/file/find.py
alexandria/file/parsers.py
alexandria/file/txt.py
alexandria/math/__init__.py
alexandria/math/algorithms.py
alexandria/math/differentiation.py
alexandria/math/functions.py
alexandria/math/integration.py
alexandria/math/interpolation.py
alexandria/math/latex.py
alexandria/math/numbers.py
alexandria/math/units.py
alexandria/shell/__init__.py
alexandria/shell/color.py
alexandria/shell/commands.py
alexandria/signals/__init__.py
alexandria/signals/control.py
alexandria/signals/standard.py
Python_Alexandria-1.990.dist-info/LICENSE
Python_Alexandria-1.990.dist-info/METADATA
Python_Alexandria-1.990.dist-info/WHEEL
Python_Alexandria-1.990.dist-info/top_level.txt
Python_Alexandria-1.990.dist-info/RECORD
