Metadata-Version: 2.1
Name: Python-Alexandria
Version: 1.990
Summary: General utilities for Python projects.
Home-page: https://github.com/alopezrivera/alexandria
Author: Antonio Lopez Rivera
Author-email: antonlopezr99@gmail.com
License: UNKNOWN
Platform: UNKNOWN
Classifier: Programming Language :: Python :: 3
Classifier: License :: OSI Approved :: MIT License
Classifier: Operating System :: OS Independent
Requires-Python: >=3.6
Requires-Dist: scipy
Requires-Dist: numpy
